tests
photostash
