Metadata-Version: 1.0
Name: photostash-client
Version: 0.0.3
Summary: Official photostash command line client
Home-page: https://github.com/seanbrant/photostash-client
Author: Sean Brant
Author-email: brant.sean@gmail.com
License: UNKNOWN
Platform: UNKNOWN
